datadis_python/__init__.py
datadis_python/client/__init__.py
datadis_python/client/base.py
datadis_python/client/datadis_client.py
datadis_python/client/unified.py
datadis_python/client/v1/__init__.py
datadis_python/client/v1/client.py
datadis_python/client/v1/simple_client.py
datadis_python/client/v2/__init__.py
datadis_python/client/v2/client.py
datadis_python/client/v2/simple_client.py
datadis_python/docs/20250920-datadis-api-reference.md
datadis_python/exceptions/__init__.py
datadis_python/models/__init__.py
datadis_python/models/consumption.py
datadis_python/models/contract.py
datadis_python/models/distributor.py
datadis_python/models/max_power.py
datadis_python/models/reactive.py
datadis_python/models/responses.py
datadis_python/models/supply.py
datadis_python/utils/__init__.py
datadis_python/utils/constants.py
datadis_python/utils/http.py
datadis_python/utils/text_utils.py
datadis_python/utils/type_converters.py
datadis_python/utils/validators.py
ctr_datadis-0.4.5.dist-info/METADATA
ctr_datadis-0.4.5.dist-info/WHEEL
ctr_datadis-0.4.5.dist-info/licenses/LICENSE
ctr_datadis-0.4.5.dist-info/RECORD
