Metadata-Version: 2.4
Name: ctr-datadis
Version: 0.4.5
Summary: SDK completo de Python para la API oficial de Datadis - Acceso programático a datos de consumo eléctrico español
License-File: LICENSE
Keywords: datadis,api,sdk,energia,consumo,electricidad,españa,cups,distribuidora
Author: CristianTacoronteRivero
Author-email: tacoronteriverocristian@gmail.com
Requires-Python: >=3.9,<4.0
Classifier: Development Status :: 5 - Production/Stable
Classifier: Intended Audience :: Developers
Classifier: License :: OSI Approved :: MIT License
Classifier: Operating System :: OS Independent
Classifier: Programming Language :: Python :: 3
Classifier: Programming Language :: Python :: 3.9
Classifier: Programming Language :: Python :: 3.10
Classifier: Programming Language :: Python :: 3.11
Classifier: Programming Language :: Python :: 3.12
Classifier: Programming Language :: Python :: 3.13
Classifier: Programming Language :: Python :: 3.14
Classifier: Topic :: Software Development :: Libraries :: Python Modules
Classifier: Topic :: Utilities
Requires-Dist: pydantic (>=2.0.0,<3.0.0)
Requires-Dist: python-dateutil (>=2.8.0,<3.0.0)
Requires-Dist: requests (>=2.28.0,<3.0.0)
Requires-Dist: typing-extensions (>=4.0.0,<5.0.0) ; python_version < "3.10"
Project-URL: Documentation, https://ctr-datadis.readthedocs.io
Project-URL: Homepage, https://github.com/TacoronteRiveroCristian/ctr-datadis
Project-URL: Repository, https://github.com/TacoronteRiveroCristian/ctr-datadis
